odoo/addons/l10n_es_aeat_sii_oca/README.rst
odoo/addons/l10n_es_aeat_sii_oca/__init__.py
odoo/addons/l10n_es_aeat_sii_oca/__manifest__.py
odoo/addons/l10n_es_aeat_sii_oca/hooks.py
odoo/addons/l10n_es_aeat_sii_oca/data/aeat_sii_map_data.xml
odoo/addons/l10n_es_aeat_sii_oca/data/aeat_sii_mapping_registration_keys_data.xml
odoo/addons/l10n_es_aeat_sii_oca/data/aeat_sii_tax_agency_data.xml
odoo/addons/l10n_es_aeat_sii_oca/data/ir_config_parameter_data.xml
odoo/addons/l10n_es_aeat_sii_oca/data/ir_cron.xml
odoo/addons/l10n_es_aeat_sii_oca/data/l10n.es.aeat.map.tax.line.tax.csv
odoo/addons/l10n_es_aeat_sii_oca/data/neutralize.sql
odoo/addons/l10n_es_aeat_sii_oca/data/template/account.fiscal.position-es_common.csv
odoo/addons/l10n_es_aeat_sii_oca/i18n/bg.po
odoo/addons/l10n_es_aeat_sii_oca/i18n/ca.po
odoo/addons/l10n_es_aeat_sii_oca/i18n/cs.po
odoo/addons/l10n_es_aeat_sii_oca/i18n/de.po
odoo/addons/l10n_es_aeat_sii_oca/i18n/es.po
odoo/addons/l10n_es_aeat_sii_oca/i18n/es_CO.po
odoo/addons/l10n_es_aeat_sii_oca/i18n/es_CR.po
odoo/addons/l10n_es_aeat_sii_oca/i18n/eu.po
odoo/addons/l10n_es_aeat_sii_oca/i18n/fr.po
odoo/addons/l10n_es_aeat_sii_oca/i18n/gl.po
odoo/addons/l10n_es_aeat_sii_oca/i18n/hr.po
odoo/addons/l10n_es_aeat_sii_oca/i18n/l10n_es_aeat_sii_oca.pot
odoo/addons/l10n_es_aeat_sii_oca/i18n/nl.po
odoo/addons/l10n_es_aeat_sii_oca/i18n/pl.po
odoo/addons/l10n_es_aeat_sii_oca/i18n/pt.po
odoo/addons/l10n_es_aeat_sii_oca/i18n/pt_BR.po
odoo/addons/l10n_es_aeat_sii_oca/i18n/ru.po
odoo/addons/l10n_es_aeat_sii_oca/i18n/sl.po
odoo/addons/l10n_es_aeat_sii_oca/i18n/sv.po
odoo/addons/l10n_es_aeat_sii_oca/i18n/tr.po
odoo/addons/l10n_es_aeat_sii_oca/i18n/vi.po
odoo/addons/l10n_es_aeat_sii_oca/models/__init__.py
odoo/addons/l10n_es_aeat_sii_oca/models/account_chart_template.py
odoo/addons/l10n_es_aeat_sii_oca/models/account_fiscal_position.py
odoo/addons/l10n_es_aeat_sii_oca/models/account_journal.py
odoo/addons/l10n_es_aeat_sii_oca/models/account_move.py
odoo_addon_l10n_es_aeat_sii_oca-18.0.1.3.6.dist-info/METADATA
odoo_addon_l10n_es_aeat_sii_oca-18.0.1.3.6.dist-info/WHEEL
odoo_addon_l10n_es_aeat_sii_oca-18.0.1.3.6.dist-info/top_level.txt
odoo_addon_l10n_es_aeat_sii_oca-18.0.1.3.6.dist-info/RECORD
