Metadata-Version: 2.1
Name: odoo-addon-l10n_es_aeat_sii_oca
Version: 18.0.1.3.6
Requires-Python: >=3.10
Requires-Dist: odoo-addon-account_invoice_refund_link==18.0.*
Requires-Dist: odoo-addon-l10n_es_aeat==18.0.*
Requires-Dist: odoo==18.0.*
Requires-Dist: requests
Requires-Dist: zeep
Summary: =?utf-8?q?Suministro_Inmediato_de_Informaci=C3=B3n_en_el_IVA?=
Home-page: https://github.com/OCA/l10n-spain
License: AGPL-3
Author: Acysos S.L.,Diagram,Minorisa,Studio73,FactorLibre,Comunitea,Otherway,Tecnativa,Javi Melendez,Sygel,Odoo Community Association (OCA)
Author-email: support@odoo-community.org
Classifier: Programming Language :: Python
Classifier: Framework :: Odoo
Classifier: Framework :: Odoo :: 18.0
Classifier: License :: OSI Approved :: GNU Affero General Public License v3
Classifier: Development Status :: 6 - Mature
